LICENSE
README.md
setup.cfg
setup.py
pysap_macro/__init__.py
pysap_macro/sap.py
pysap_macro.egg-info/PKG-INFO
pysap_macro.egg-info/SOURCES.txt
pysap_macro.egg-info/dependency_links.txt
pysap_macro.egg-info/requires.txt
pysap_macro.egg-info/top_level.txt