Metadata-Version: 2.1
Name: pysap-macro
Version: 0.1
Summary: Library to run SAP scripts with Python
Home-page: https://github.com/teusinLS/sapy_script
Author: Mateus Lima Silva
Author-email: mateusls.personal@gmail.com
License: UNKNOWN
Keywords: SAP Script Python
Platform: UNKNOWN
Classifier: Development Status :: 3 - Alpha
Classifier: Intended Audience :: Developers
Classifier: License :: OSI Approved :: MIT License
Classifier: Operating System :: Microsoft :: Windows :: Windows 7
Classifier: Operating System :: Microsoft :: Windows :: Windows 8
Classifier: Operating System :: Microsoft :: Windows :: Windows 8.1
Classifier: Operating System :: Microsoft :: Windows :: Windows 10
Classifier: Programming Language :: Python
License-File: LICENSE
